windmill/__init__.py
windmill/__main__.py
windmill/cli/__init__.py
windmill/cli/cli.py
windmill/config/__init__.py
windmill/config/base_config.py
windmill/config/project_config.py
windmill/config/run_config.py
windmill/constants.py
windmill/exceptions.py
windmill/http/__init__.py
windmill/http/api/__init__.py
windmill/http/api/endpoints.py
windmill/http/app/.gitignore
windmill/http/app/README.md
windmill/http/app/dist/App.da27a0d5.js
windmill/http/app/dist/App.da27a0d5.js.map
windmill/http/app/dist/index.html
windmill/http/app/package-lock.json
windmill/http/app/package.json
windmill/http/app/public/index.html
windmill/http/app/src/ApiClient.tsx
windmill/http/app/src/App.tsx
windmill/http/app/src/components/Airflow/AirflowDag.tsx
windmill/http/app/src/components/Airflow/AirflowNode.tsx
windmill/http/app/src/components/Airflow/AirflowOperator.tsx
windmill/http/app/src/components/Airflow/AirflowSidebar.tsx
windmill/http/app/src/components/Airflow/index.ts
windmill/http/app/src/components/Navbar/Navbar.tsx
windmill/http/app/src/components/Navbar/NavbarDropdowns.tsx
windmill/http/app/src/components/Navbar/index.ts
windmill/http/app/src/components/Page/FileBrowser.tsx
windmill/http/app/src/components/Page/MainPage.tsx
windmill/http/app/src/components/Page/Page.tsx
windmill/http/app/src/components/Page/RenameBox.tsx
windmill/http/app/src/components/Page/ResizablePanel.tsx
windmill/http/app/src/components/Page/index.ts
windmill/http/app/src/components/Sidebar/SelectedSidebar.tsx
windmill/http/app/src/components/Sidebar/index.ts
windmill/http/app/src/components/Theme.tsx
windmill/http/app/src/components/index.ts
windmill/http/app/src/index.ts
windmill/http/app/src/misc/defaultChartState.ts
windmill/http/app/src/misc/icon.tsx
windmill/http/app/tsconfig.json
windmill/models/__init__.py
windmill/models/dags/__init__.py
windmill/models/dags/dag_handler.py
windmill/models/operators/__init__.py
windmill/models/operators/operator_handler.py
windmill_airflow-0.0.2.dist-info/entry_points.txt
windmill_airflow-0.0.2.dist-info/LICENSE
windmill_airflow-0.0.2.dist-info/WHEEL
windmill_airflow-0.0.2.dist-info/METADATA
windmill_airflow-0.0.2.dist-info/RECORD
