Metadata-Version: 2.1
Name: windmill-airflow
Version: 0.0.2
Summary: 
License: Apache-2.0
Author: mayansalama
Author-email: micsalama@gmail.com
Requires-Python: >=3.6,<4.0
Classifier: License :: OSI Approved :: Apache Software License
Classifier: Programming Language :: Python :: 3
Classifier: Programming Language :: Python :: 3.6
Classifier: Programming Language :: Python :: 3.7
Requires-Dist: apache-airflow[crypto,celery,postgres,hive,jdbc,mysql,ssh] (==1.10.4)
Requires-Dist: decli (>=0.5.0,<0.6.0)
Requires-Dist: docstring-parser (>=0.3.0,<0.4.0)
Requires-Dist: flask-cors (>=3.0.8,<4.0.0)
Requires-Dist: marshmallow (>=3.0,<4.0)
Requires-Dist: pyyaml (>=5.1.2,<6.0.0)
